<ArrayOfNft xmlns:xsd="http://www.w3.org/2001/XMLSchema" xmlns:xsi="http://www.w3.org/2001/XMLSchema-instance">
  <Nft>
    <Name>CryptoPunk #4156</Name>
    <Url>https://www.nft-stats.com/asset/0xb47e3cd837ddf8e4c57f05d70ab865de6e193bbb/4156</Url>
    <DateTimeSold>2022-08-31T17:47:06.4848347+02:00</DateTimeSold>
    <PriceUsd>15000</PriceUsd>
    <Collection>
      <Name>CryptoPunks</Name>
      <Url>https://www.nft-stats.com/collection/cryptopunks</Url>
    </Collection>
  </Nft>
  <Nft>
    <Name>Right-click and Save As guy</Name>
    <Url>https://www.nft-stats.com/asset/0x41a322b28d0ff354040e2cbc676f0320d8c8850d/1154</Url>
    <DateTimeSold>2022-08-31T17:47:06.4848347+02:00</DateTimeSold>
    <PriceUsd>7000</PriceUsd>
    <Collection>
      <Name>SuperRare</Name>
      <Url>https://www.nft-stats.com/collection/superrare</Url>
    </Collection>
  </Nft>
  <Nft>
    <Name>Ross Ulbricht Genesis Collection</Name>
    <Url>https://www.nft-stats.com/asset/0xb932a70a57673d89f4acffbe830e8ed7f75fb9e0/30841</Url>
    <DateTimeSold>2022-08-31T17:47:06.4848347+02:00</DateTimeSold>
    <PriceUsd>5000000</PriceUsd>
    <Collection>
      <Name>SuperRare</Name>
      <Url>https://www.nft-stats.com/collection/superrare</Url>
    </Collection>
  </Nft>
  <Nft>
    <Name>CryptoPunk #2964</Name>
    <Url>https://www.nft-stats.com/asset/0xb47e3cd837ddf8e4c57f05d70ab865de6e193bbb/2964</Url>
    <DateTimeSold>2022-08-31T17:47:06.4848347+02:00</DateTimeSold>
    <PriceUsd>9000</PriceUsd>
    <Collection>
      <Name>CryptoPunks</Name>
      <Url>https://www.nft-stats.com/collection/cryptopunks</Url>
    </Collection>
  </Nft>
  <Nft>
    <Name>Bored Ape Yacht Club</Name>
    <Url>https://www.nft-stats.com/asset/0xbc4ca0eda7647a8ab7c2061c2e118a18a936f13d/9452</Url>
    <DateTimeSold>2022-08-31T17:47:06.4848347+02:00</DateTimeSold>
    <PriceUsd>7650</PriceUsd>
    <Collection>
      <Name>Bored Ape Yacht Club</Name>
      <Url>https://www.nft-stats.com/collection/boredapeyachtclub</Url>
    </Collection>
  </Nft>
</ArrayOfNft>